kirimemail_smtp/__init__.py
kirimemail_smtp/api/__init__.py
kirimemail_smtp/api/credentials.py
kirimemail_smtp/api/domains.py
kirimemail_smtp/api/logs.py
kirimemail_smtp/api/messages.py
kirimemail_smtp/api/suppressions.py
kirimemail_smtp/client/__init__.py
kirimemail_smtp/client/smtp_client.py
kirimemail_smtp/exceptions/__init__.py
kirimemail_smtp/exceptions/api_exception.py
kirimemail_smtp/exceptions/authentication_exception.py
kirimemail_smtp/exceptions/not_found_exception.py
kirimemail_smtp/exceptions/server_exception.py
kirimemail_smtp/exceptions/validation_exception.py
kirimemail_smtp/models/__init__.py
kirimemail_smtp/models/credential.py
kirimemail_smtp/models/domain.py
kirimemail_smtp/models/log_entry.py
kirimemail_smtp/models/pagination.py
kirimemail_smtp/models/suppression.py
kirimemail_smtp_sdk-1.0.0.dist-info/METADATA
kirimemail_smtp_sdk-1.0.0.dist-info/WHEEL
kirimemail_smtp_sdk-1.0.0.dist-info/licenses/LICENSE
kirimemail_smtp_sdk-1.0.0.dist-info/RECORD
