Metadata-Version: 2.4
Name: kirimemail-smtp-sdk
Version: 1.0.0
Summary: Python SDK for Kirim.Email SMTP API
Project-URL: Homepage, https://github.com/kirimemail/kirimemail-smtp-python-sdk
Project-URL: Repository, https://github.com/kirimemail/kirimemail-smtp-python-sdk
Project-URL: Issues, https://github.com/kirimemail/kirimemail-smtp-python-sdk/issues
Project-URL: Documentation, https://github.com/kirimemail/kirimemail-smtp-python-sdk#readme
Author-email: "Kirim.Email" <support@kirim.email>
License: MIT
License-File: LICENSE
Keywords: api,email,kirim-email,sdk,smtp,transactional-email
Classifier: Development Status :: 5 - Production/Stable
Classifier: Intended Audience :: Developers
Classifier: License :: OSI Approved :: MIT License
Classifier: Programming Language :: Python :: 3
Classifier: Programming Language :: Python :: 3.9
Classifier: Programming Language :: Python :: 3.10
Classifier: Programming Language :: Python :: 3.11
Classifier: Programming Language :: Python :: 3.12
Classifier: Topic :: Communications :: Email
Classifier: Topic :: Software Development :: Libraries :: Python Modules
Requires-Python: >=3.9
Requires-Dist: httpx>=0.25.0
Requires-Dist: pydantic>=2.0.0
Provides-Extra: dev
Requires-Dist: mypy>=1.0.0; extra == 'dev'
Requires-Dist: pytest-asyncio>=0.21.0; extra == 'dev'
Requires-Dist: pytest-cov>=4.0.0; extra == 'dev'
Requires-Dist: pytest>=7.0.0; extra == 'dev'
Requires-Dist: respx>=0.20.0; extra == 'dev'
Requires-Dist: ruff>=0.1.0; extra == 'dev'
Provides-Extra: test
Requires-Dist: pytest-asyncio>=0.21.0; extra == 'test'
Requires-Dist: pytest-cov>=4.0.0; extra == 'test'
Requires-Dist: pytest>=7.0.0; extra == 'test'
Requires-Dist: respx>=0.20.0; extra == 'test'
